README.rst
setup.py
lesscache/__init__.py
lesscache/cache.py
lesscache/dynamodb.py
lesscache/exceptions.py
lesscache/helper.py
lesscache/settings.py
lesscache.egg-info/PKG-INFO
lesscache.egg-info/SOURCES.txt
lesscache.egg-info/dependency_links.txt
lesscache.egg-info/not-zip-safe
lesscache.egg-info/requires.txt
lesscache.egg-info/top_level.txt
lesscache/compact/__init__.py
lesscache/compact/flask.py
lesscache/compact/django/__init__.py
lesscache/compact/django/cache.py
lesscache/compact/django/models.py
lesscache/encode/__init__.py
lesscache/encode/base.py
lesscache/encode/pickle.py
tests/__init__.py
tests/test_cache_simple.py
tests/test_create_table.py
tests/test_settings.py
tests/django/__init__.py
tests/django/settings.py
tests/django/urls.py
tests/django/view.py
tests/django/wsgi.py