Metadata-Version: 1.1
Name: lesscache
Version: 0.1
Summary: AWS Dynamodb as cache backend for Django and Flask
Home-page: http://github.com/ebertti/lesscache/
Author: Estante Virtual
Author-email: ebertti@gmail.com
License: MIT License
Keywords: cache,django,flask,aws,dynamodb
Platform: OS Independent
Classifier: Development Status :: 3 - Alpha
Classifier: Framework :: Django
Classifier: Intended Audience :: Developers
Classifier: License :: OSI Approved :: MIT License
Classifier: Natural Language :: English
Classifier: Natural Language :: Portuguese (Brazilian)
Classifier: Operating System :: OS Independent
Classifier: Programming Language :: Python :: 3
Classifier: Programming Language :: Python :: 3.6
